hello.py
minimal_package-0.1.dist-info/METADATA
minimal_package-0.1.dist-info/WHEEL
minimal_package-0.1.dist-info/top_level.txt
minimal_package-0.1.dist-info/RECORD
