Metadata-Version: 2.4
Name: minimal_package
Version: 0.1
Summary: A minimal Python package with one file
Dynamic: summary
